LICENSE
MANIFEST.in
README.md
setup.py
hxgvtdjmab/__init__.py
hxgvtdjmab/api_helper.py
hxgvtdjmab/configuration.py
hxgvtdjmab/decorators.py
hxgvtdjmab/hxgvtdjmab_client.py
hxgvtdjmab.egg-info/PKG-INFO
hxgvtdjmab.egg-info/SOURCES.txt
hxgvtdjmab.egg-info/dependency_links.txt
hxgvtdjmab.egg-info/requires.txt
hxgvtdjmab.egg-info/top_level.txt
hxgvtdjmab/controllers/__init__.py
hxgvtdjmab/controllers/api_controller.py
hxgvtdjmab/controllers/base_controller.py
hxgvtdjmab/exceptions/__init__.py
hxgvtdjmab/exceptions/api_exception.py
hxgvtdjmab/http/__init__.py
hxgvtdjmab/http/http_call_back.py
hxgvtdjmab/http/http_client.py
hxgvtdjmab/http/http_context.py
hxgvtdjmab/http/http_method_enum.py
hxgvtdjmab/http/http_request.py
hxgvtdjmab/http/http_response.py
hxgvtdjmab/http/requests_client.py
hxgvtdjmab/http/auth/__init__.py
hxgvtdjmab/http/auth/basic_auth.py
hxgvtdjmab/models/__init__.py
hxgvtdjmab/models/suite_code_enum.py
tests/__init__.py
tests/http_response_catcher.py
tests/test_helper.py
tests/controllers/__init__.py
tests/controllers/controller_test_base.py
tests/controllers/test_api_controller.py